{"cameraMode":{"drawMode":0,"name":"Shaded","section":"Shading Mode"},"sceneLighting":true,"audioPlay":false,"sceneViewState":{"showFog":true,"showMaterialUpdate":false,"showSkybox":true,"showFlares":true,"showImageEffects":true,"showParticleSystems":true,"showVisualEffectGraphs":true,"m_FxEnabled":true},"in2DMode":false,"pivot":{"x":-17.19004249572754,"y":-49.82911682128906,"z":30.769702911376954},"rotation":{"x":-0.3896324038505554,"y":0.4468899369239807,"z":-0.22521398961544038,"w":-0.773146390914917},"size":83.34709930419922,"orthographic":false}